lammps_helper/__init__.py
lammps_helper/lammps_helper.py
lammps_helper_pkg/__init__.py
lammps_helper_pkg/lammps_helper.py
lammps_helper-0.1.4.dist-info/LICENSE
lammps_helper-0.1.4.dist-info/METADATA
lammps_helper-0.1.4.dist-info/WHEEL
lammps_helper-0.1.4.dist-info/top_level.txt
lammps_helper-0.1.4.dist-info/RECORD
